layer_to_layer_pytorch/__init__.py
layer_to_layer_pytorch/__main__.py
layer_to_layer_pytorch/helpers.py
layer_to_layer_pytorch/l2l.py
layer_to_layer_pytorch/py.typed
layer_to_layer_pytorch/types.py
layer_to_layer_pytorch-0.3.0.dist-info/entry_points.txt
layer_to_layer_pytorch-0.3.0.dist-info/LICENSE
layer_to_layer_pytorch-0.3.0.dist-info/WHEEL
layer_to_layer_pytorch-0.3.0.dist-info/METADATA
layer_to_layer_pytorch-0.3.0.dist-info/RECORD
