Metadata-Version: 2.1
Name: layer-to-layer-pytorch
Version: 0.3.0
Summary: PyTorch implementation of L2L execution algorithm
Home-page: https://github.com/TezRomacH/layer-to-layer-pytorch
License: MIT
Author: Roman Tezikov
Author-email: tez.romach@gmail.com
Requires-Python: >=3.7,<4.0
Classifier: Development Status :: 3 - Alpha
Classifier: Intended Audience :: Developers
Classifier: License :: OSI Approved :: MIT License
Classifier: Operating System :: OS Independent
Classifier: Programming Language :: Python :: 3
Classifier: Programming Language :: Python :: 3.7
Classifier: Programming Language :: Python :: 3.8
Classifier: Topic :: Software Development :: Libraries :: Python Modules
Requires-Dist: importlib_metadata (>=1.6.0,<2.0.0); python_version < "3.8"
Requires-Dist: numpy (>=1.19.1,<2.0.0)
Requires-Dist: torch (>=1.6.0,<2.0.0)
Requires-Dist: tqdm (>=4.48.2,<5.0.0)
Requires-Dist: typer[all] (>=0.3.2,<0.4.0)
Project-URL: Repository, https://github.com/TezRomacH/layer-to-layer-pytorch
